kungfupipelines/__init__.py
kungfupipelines/cli.py
kungfupipelines/step.py
kungfupipelines/step_test.py
kungfupipelines/workflow.py
kungfupipelines/workflow_test.py
kung_fu_pipelines-0.1.6.dist-info/LICENSE
kung_fu_pipelines-0.1.6.dist-info/WHEEL
kung_fu_pipelines-0.1.6.dist-info/METADATA
kung_fu_pipelines-0.1.6.dist-info/RECORD
